LICENSE.txt
MANIFEST.in
README.md
setup.py
regenwolken/__init__.py
regenwolken/manage.py
regenwolken/mongonic.py
regenwolken/specs.py
regenwolken/utils.py
regenwolken/views.py
regenwolken.egg-info/PKG-INFO
regenwolken.egg-info/SOURCES.txt
regenwolken.egg-info/dependency_links.txt
regenwolken.egg-info/entry_points.txt
regenwolken.egg-info/not-zip-safe
regenwolken.egg-info/requires.txt
regenwolken.egg-info/top_level.txt
regenwolken/static/MIT-LICENSE
regenwolken/static/favicon.ico
regenwolken/static/robots.txt
regenwolken/static/images/favicon.ico
regenwolken/static/images/regenwolken.png
regenwolken/static/images/embed/image/badge-2x.png
regenwolken/static/images/embed/image/badge.png
regenwolken/static/images/embed/image/body-bg-2x.png
regenwolken/static/images/embed/image/body-bg.png
regenwolken/static/images/embed/image/embed-2x.png
regenwolken/static/images/embed/image/embed.png
regenwolken/static/images/embed/image/header-bg.png
regenwolken/static/images/embed/other/badge-2x.png
regenwolken/static/images/embed/other/badge.png
regenwolken/static/images/embed/other/body-bg-2x.png
regenwolken/static/images/embed/other/body-bg.png
regenwolken/static/images/embed/other/thumbs-2x.png
regenwolken/static/images/embed/other/thumbs.png
regenwolken/static/images/embed/other/view-button-2x.png
regenwolken/static/images/embed/other/view-button.png
regenwolken/static/images/embed/text/badge-2x.png
regenwolken/static/images/embed/text/badge.png
regenwolken/static/images/embed/text/body-bg.png
regenwolken/static/images/embed/text/embed-2x.png
regenwolken/static/images/embed/text/embed.png
regenwolken/static/images/embed/text/header-bg.png
regenwolken/static/images/item_types/LICENCE
regenwolken/static/images/item_types/archive.png
regenwolken/static/images/item_types/audio.png
regenwolken/static/images/item_types/bookmark.png
regenwolken/static/images/item_types/image.png
regenwolken/static/images/item_types/text.png
regenwolken/static/images/item_types/trash.png
regenwolken/static/images/item_types/unknown.png
regenwolken/static/images/item_types/video.png
regenwolken/static/javascripts/image.js
regenwolken/static/javascripts/other.js
regenwolken/static/javascripts/vendor/jquery-1.6.1.min.js
