Metadata-Version: 1.1
Name: regenwolken
Version: 0.6.2
Summary: open source, self-hosting CloudApp
Home-page: http://pypi.python.org/pypi/regenwolken/
Author: posativ
Author-email: info@posativ.org
License: BSD revised
Platform: UNKNOWN
Classifier: Development Status :: 4 - Beta
Classifier: Topic :: Internet
Classifier: Topic :: Internet :: WWW/HTTP :: Dynamic Content
Classifier: License :: OSI Approved :: BSD License
Classifier: Programming Language :: Python :: 2.6
Classifier: Programming Language :: Python :: 2.7
